odoo/addons/stock_cubiscan/README.rst
odoo/addons/stock_cubiscan/__init__.py
odoo/addons/stock_cubiscan/__manifest__.py
odoo/addons/stock_cubiscan/data/uom.xml
odoo/addons/stock_cubiscan/i18n/stock_cubiscan.pot
odoo/addons/stock_cubiscan/models/__init__.py
odoo/addons/stock_cubiscan/models/cubiscan.py
odoo/addons/stock_cubiscan/models/stock.py
odoo/addons/stock_cubiscan/readme/CONFIGURE.rst
odoo/addons/stock_cubiscan/readme/CONTRIBUTORS.rst
odoo/addons/stock_cubiscan/readme/DESCRIPTION.rst
odoo/addons/stock_cubiscan/readme/ROADMAP.rst
odoo/addons/stock_cubiscan/readme/USAGE.rst
odoo/addons/stock_cubiscan/scripts/cubiscan_stub.py
odoo/addons/stock_cubiscan/security/ir.model.access.csv
odoo/addons/stock_cubiscan/static/description/icon.png
odoo/addons/stock_cubiscan/static/description/index.html
odoo/addons/stock_cubiscan/static/src/scss/cubiscan_wizard.scss
odoo/addons/stock_cubiscan/tests/__init__.py
odoo/addons/stock_cubiscan/tests/test_cubiscan.py
odoo/addons/stock_cubiscan/tests/test_cubiscan_wizard.py
odoo/addons/stock_cubiscan/views/assets.xml
odoo/addons/stock_cubiscan/views/cubiscan_view.xml
odoo/addons/stock_cubiscan/wizard/__init__.py
odoo/addons/stock_cubiscan/wizard/cubiscan_wizard.py
odoo/addons/stock_cubiscan/wizard/cubiscan_wizard.xml
odoo13_addon_stock_cubiscan-13.0.1.1.1.dist-info/METADATA
odoo13_addon_stock_cubiscan-13.0.1.1.1.dist-info/WHEEL
odoo13_addon_stock_cubiscan-13.0.1.1.1.dist-info/top_level.txt
odoo13_addon_stock_cubiscan-13.0.1.1.1.dist-info/RECORD
